{
  "en": {
    "[\\\\u4E00-\\\\u9FA5|\\\\uFF5C|\\\\uff1b|\\\\uff1a|\\\\u201d|\\\\u201c|\\\\u2019|\\\\u3002|\\\\uff0c|\\\\u0020|\\\\u3001|\\\\uff1f|\\\\uff5c|\\\\uff08|\\\\uff09|\\\\u3010|\\\\u3011|\\\\uff1a|\\\\uff01]+": "[\\\\u4E00-\\\\u9FA5|\\\\uFF5C|\\\\uff1b|\\\\uff1a|\\\\u201d|\\\\u201c|\\\\u2019|\\\\u3002|\\\\uff0c|\\\\u0020|\\\\u3001|\\\\uff1f|\\\\uff5c|\\\\uff08|\\\\uff09|\\\\u3010|\\\\u3011|\\\\uff1a|\\\\uff01]+",
    "[{language: 3, mode:1},{language: 4, mode:2},{language: 5, mode:2}]": "[{language: 3, mode:1},{language: 4, mode:2},{language: 5, mode:2}]",
    "\\\"": "\\\"",
    "\\## ### ### ## ##": "\\## ### ### ## ##",
    "\\#36363899": "\\#36363899",
    "\\?": "\\?",
    "\\@": "\\@",
    "^(([0-1]?[0-9])|([2][0-3])):([0-5]?[0-9])(:([0-5]?[0-9]))?$": "^(([0-1]?[0-9])|([2][0-3])):([0-5]?[0-9])(:([0-5]?[0-9]))?$",
    "^(Hi point).*|.*(Hi point)$|.*[(fm)(FM)(Broadcasting)(Radio)()].*": "^(Hi point).*|.*(Hi point)$|.*[(fm)(FM)(Broadcasting)(Radio)()].*",
    "active yellow": "Жёлтый",
    "android.*": "android.*",
    "app-maps@support.yandex.ru": "app-maps@support.yandex.ru",
    "app-navigator@support.yandex.ru": "app-navigator@support.yandex.ru",
    "bean red": "Красный боб",
    "black": "Чёрный",
    "blue": "Синий",
    "bluetooth connecting…": "Подключение Bluetooth…",
    "button": "Кнопка",
    "button path": "Путь кнопки",
    "c241ffbc8e287c4e9a4ad19632ba1b1351ad361d5177b7d7b29859bd2b7fc631, com.google.android.apps.automotive.templates.host": "c241ffbc8e287c4e9a4ad19632ba1b1351ad361d5177b7d7b29859bd2b7fc631, com.google.android.apps.automotive.templates.host",
    "ca-app-pub-0883711335365599/1174715345": "ca-app-pub-0883711335365599/1174715345",
    "ca-app-pub-0883711335365599/3347586407": "ca-app-pub-0883711335365599/3347586407",
    "ca-app-pub-0883711335365599~8697982142": "ca-app-pub-0883711335365599~8697982142",
    "captcha": "Капча",
    "city id": "ID города",
    "city name": "Город",
    "com.android.*": "com.android.*",
    "com.android.car.messenger/.MessengerService#bind=startForeground,user=foreground,trigger=userUnlocked": "com.android.car.messenger/.MessengerService#bind=startForeground,user=foreground,trigger=userUnlocked",
    "com.google.android.car.*": "com.google.android.car.*",
    "com.mega.*": "com.mega.*",
    "com.yandex.passporr.sync.": "com.yandex.passporr.sync.",
    "com.yandex.passport.sync.": "com.yandex.passport.sync.",
    "country id": "ID страны",
    "cubic-bezier(0, 0, 0, 1)": "cubic-bezier(0, 0, 0, 1)",
    "cubic-bezier(0, 0, 0.2, 1)": "cubic-bezier(0, 0, 0.2, 1)",
    "cubic-bezier(0, 0, 1, 1)": "cubic-bezier(0, 0, 1, 1)",
    "cubic-bezier(0.1, 0.7, 0.1, 1)": "cubic-bezier(0.1, 0.7, 0.1, 1)",
    "cubic-bezier(0.2, 0, 0, 1)": "cubic-bezier(0.2, 0, 0, 1)",
    "cubic-bezier(0.3, 0, 0.8, 0.2)": "cubic-bezier(0.3, 0, 0.8, 0.2)",
    "cubic-bezier(0.3, 0, 1, 1)": "cubic-bezier(0.3, 0, 1, 1)",
    "cubic-bezier(0.4, 0, 0.2, 1)": "cubic-bezier(0.4, 0, 0.2, 1)",
    "cubic-bezier(0.4, 0, 1, 1)": "cubic-bezier(0.4, 0, 1, 1)",
    "custom ip address": "Свой IP-адрес",
    "d MMMM": "d MMMM",
    "d MMMM y, HH:mm": "d MMMM y, HH:mm",
    "dark": "Тёмная",
    "dark grey": "Тёмно-серый",
    "dd66deaf312d8daec7adbe85a218ecc8c64f3b152f9b5998d5b29300c2623f61, com.google.android.apps.automotive.templates.host": "dd66deaf312d8daec7adbe85a218ecc8c64f3b152f9b5998d5b29300c2623f61, com.google.android.apps.automotive.templates.host",
    "diagnostic": "Диагностика",
    "diagnostics info": "Диагностика",
    "domain": "Домен",
    "email": "E-mail",
    "email@rambler.ru": "email@rambler.ru",
    "f/%1$,.1f": "f/%1$,.1f",
    "fdb00c43dbde8b51cb312aa81d3b5fa17713adb94b28f598d77f8eb89daceedf, com.google.android.projection.gearhead": "fdb00c43dbde8b51cb312aa81d3b5fa17713adb94b28f598d77f8eb89daceedf, com.google.android.projection.gearhead",
    "ft. %s": "при уч. %s",
    "green": "Зелёный",
    "grey 1": "Серый 1",
    "grey 2": "Серый 2",
    "grey 3": "Серый 3",
    "icon": "Значок",
    "icon path": "Путь значка",
    "ip address": "IP-адрес",
    "left": "Слева",
    "location(city)": "Город",
    "login": "Вход",
    "loud": "Громко",
    "many": "Много",
    "model": "Модель",
    "navimaps": "navimaps",
    "non-interactive feedback": "Неинтерактивный отзыв",
    "normal": "Обычная",
    "occupantZoneId=0,occupantType=DRIVER,seatRow=1,seatSide=driver": "occupantZoneId=0,occupantType=DRIVER,seatRow=1,seatSide=driver",
    "oname": "oname",
    "open store update screen(Available)": "Экран обновления (доступно)",
    "open store update screen(Not available)": "Экран обновления (недоступно)",
    "other": "Другое",
    "passport-rc.yandex.ru": "passport-rc.yandex.ru",
    "passport.yandex-team.ru": "passport.yandex-team.ru",
    "password": "Пароль",
    "peachy yellow": "Персиковый",
    "pnum, lnum": "pnum, lnum",
    "power off": "Выключение питания",
    "premier": "Премьер",
    "price": "Стоимость",
    "production": "Продакшн",
    "rating": "Рейтинг",
    "rating %s and %s": "Рейтинг %s и %s",
    "region id": "ID региона",
    "review count": "Отзывов",
    "runtime": "Длительность",
    "samsung": "Samsung",
    "screen off": "Экран ВЫКЛ",
    "sec unitl your reward": "сек. до награды",
    "sponsored": "Реклама",
    "subscribe": "Подписаться",
    "subscribed": "Вы подписаны",
    "test string, delete me": "Тестовая строка, удалите",
    "the device dose not support": "Устройство не поддерживается",
    "the new white": "Новый белый",
    "to get the AI Fengxing APP": "для приложения AI Fengxing",
    "tpns": "tpns",
    "unsubscribe": "Отписаться",
    "unsubscribed": "Отписка выполнена",
    "vendor": "Производитель",
    "violet": "Фиолетовый",
    "votes": "Голосов",
    "web_cookie_is_available: %b": "web_cookie_is_available: %b",
    "white": "Белый",
    "will be added to your collection in Yandex Music": "Добавится в коллекцию в Яндекс Музыке",
    "without DRM": "Без DRM",
    "without subtitles": "Без субтитров",
    "yandexmusic-d5848.firebasestorage.app": "yandexmusic-d5848.firebasestorage.app",
    "year": "Год",
    "you camera": "Камера",
    "your current location": "Ваше местоположение",
    "your microphone": "Микрофон",
    "~%1$s": "~%1$s",
    "¥36000": "¥36000",
    "© %1$s": "© %1$s",
    "© 2010–%1$s Yango": "© 2010–%1$s Yango",
    "© 2025 Yandex Music": "© 2025 Яндекс Музыка",
    "«%s»": "«%s»",
    "Çok özür dilerim ama internet gitmiş gibi. Maalesef internet olmayınca yapamam.": "Извините, похоже, нет интернета. Без сети ничего не получится.",
    "Ümit Sayman": "Ümit Sayman",
    "Český překlad": "Чешский перевод",
    "Čeština": "Чешский",
    "Ελληνικά": "Греческий",
    "– Pending_action: %s": "– Ожидающее действие: %s",
    "– State: %s": "– Состояние: %s",
    "– deviceId: %s": "– deviceId: %s",
    "– puid: %s": "– puid: %s",
    "– push_token_platform: %s": "– push_token_platform: %s",
    "– subscriptionId: %s": "– subscriptionId: %s",
    "– uuid: %s": "– uuid: %s",
    "•• %1$s": "•• %1$s",
    "•••• %1$s": "•••• %1$s",
    "⁦18+⁩": "18+",
    "🐝 Debug Panel": "🐝 Отладка",
    "[{ \\\"include\\\": \\\"https://passport.yandex.ru/.well-known/assetlinks.json\\\" }]": "[{ \\\"include\\\": \\\"https://passport.yandex.ru/.well-known/assetlinks.json\\\" }]",
    "[{ \\\"relation\\\": [\\\"delegate_permission/common.handle_all_urls\\\"], \\\"target\\\": { \\\"namespace\\\": \\\"web\\\", \\\"site\\\": \\\"https://kinopoisk.ru\\\" } }, { \\\"include\\\": \\\"https://passport.yandex.ru/.well-known/assetlinks.json\\\" }]": "[{ \\\"relation\\\": [\\\"delegate_permission/common.handle_all_urls\\\"], \\\"target\\\": { \\\"namespace\\\": \\\"web\\\", \\\"site\\\": \\\"https://kinopoisk.ru\\\" } }, { \\\"include\\\": \\\"https://passport.yandex.ru/.well-known/assetlinks.json\\\" }]",
    "\\\\d+(.\\\\d+){0,1}(x|X)": "\\\\d+(.\\\\d+){0,1}(x|X)",
    "\\\\d{4}-?\\\\d{8}|\\\\d{4}-\\\\d{7}": "\\\\d{4}-?\\\\d{8}|\\\\d{4}-\\\\d{7}",
    "\\\\s+": "\\\\s+",
    "^\\\\w+$": "^\\\\w+$",
    "№ %1$s · %2$s (%3$s)": "№ %1$s · %2$s (%3$s)"
  }
}
